autowrap/Code.py
autowrap/CodeGenerator.py
autowrap/ConversionProvider.py
autowrap/DeclResolver.py
autowrap/Main.py
autowrap/PXDParser.py
autowrap/Types.py
autowrap/Utils.py
autowrap/__init__.py
autowrap/run.py
autowrap/version.py
autowrap/data_files/__init__.py
autowrap/data_files/autowrap/ArrayWrappers.pyx
autowrap/data_files/autowrap/AutowrapConstPtrHolder.pxd
autowrap/data_files/autowrap/AutowrapPtrHolder.pxd
autowrap/data_files/autowrap/AutowrapRefHolder.pxd
autowrap/data_files/autowrap/autowrap_tools.hpp
autowrap-0.27.0.dist-info/licenses/LICENSE
autowrap-0.27.0.dist-info/METADATA
autowrap-0.27.0.dist-info/WHEEL
autowrap-0.27.0.dist-info/entry_points.txt
autowrap-0.27.0.dist-info/top_level.txt
autowrap-0.27.0.dist-info/RECORD
