Metadata-Version: 2.4
Name: autowrap
Version: 0.27.0
Summary: Generates Python Extension modules from commented Cython PXD files
Author-email: "OpenMS Inc." <webmaster@openms.de>
Maintainer-email: "OpenMS Inc." <webmaster@openms.de>
License-Expression: BSD-3-Clause
Project-URL: Homepage, https://github.com/OpenMS/autowrap
Project-URL: Repository, https://github.com/OpenMS/autowrap
Project-URL: Documentation, https://github.com/OpenMS/autowrap/blob/master/docs/README.md
Project-URL: Changelog, https://github.com/OpenMS/autowrap/blob/master/HISTORY.md
Project-URL: Bug Tracker, https://github.com/OpenMS/autowrap/issues
Classifier: Development Status :: 3 - Alpha
Classifier: Intended Audience :: Developers
Classifier: Operating System :: OS Independent
Classifier: Programming Language :: Python :: 3
Classifier: Programming Language :: Python :: 3.9
Classifier: Programming Language :: Python :: 3.10
Classifier: Programming Language :: Python :: 3.11
Classifier: Programming Language :: Python :: 3.12
Classifier: Programming Language :: Python :: 3.13
Classifier: Topic :: Software Development :: Code Generators
Requires-Python: >=3.9
License-File: LICENSE
Requires-Dist: Cython>=3.1
Requires-Dist: setuptools
Provides-Extra: dev
Requires-Dist: pytest>=6.0; extra == "dev"
Requires-Dist: pytest-cov; extra == "dev"
Requires-Dist: black; extra == "dev"
Requires-Dist: ruff; extra == "dev"
Requires-Dist: mypy; extra == "dev"
Requires-Dist: build; extra == "dev"
Requires-Dist: twine; extra == "dev"
Requires-Dist: numpy>=1.20; extra == "dev"
Provides-Extra: test
Requires-Dist: pytest>=6.0; extra == "test"
Requires-Dist: pytest-cov; extra == "test"
Requires-Dist: numpy>=1.20; extra == "test"
Dynamic: license-file
